{"header" : {
  "cloc_url"           : "github.com/AlDanial/cloc",
  "cloc_version"       : "1.84",
  "elapsed_seconds"    : 0.353059053421021,
  "n_files"            : 2,
  "n_lines"            : 40,
  "files_per_second"   : 5.66477471862197,
  "lines_per_second"   : 113.295494372439,
  "report_file"        : "loc/flathub__org.tordini.flavio.Minitube.json"},
"JSON" :{
  "nFiles": 2,
  "blank": 0,
  "comment": 0,
  "code": 40},
"SUM": {
  "blank": 0,
  "comment": 0,
  "code": 40,
  "nFiles": 2} }
