{"header" : {
  "cloc_url"           : "github.com/AlDanial/cloc",
  "cloc_version"       : "1.84",
  "elapsed_seconds"    : 3.89174699783325,
  "n_files"            : 21,
  "n_lines"            : 1813,
  "files_per_second"   : 5.39603422619503,
  "lines_per_second"   : 465.857621528171,
  "report_file"        : "loc/snwfdhmp__duck.json"},
"Go" :{
  "nFiles": 18,
  "blank": 256,
  "comment": 108,
  "code": 1194},
"Markdown" :{
  "nFiles": 1,
  "blank": 75,
  "comment": 0,
  "code": 158},
"YAML" :{
  "nFiles": 1,
  "blank": 1,
  "comment": 1,
  "code": 17},
"Bourne Shell" :{
  "nFiles": 1,
  "blank": 1,
  "comment": 0,
  "code": 2},
"SUM": {
  "blank": 333,
  "comment": 109,
  "code": 1371,
  "nFiles": 21} }
